{
  "_class": "shapePath",
  "booleanOperation": -1,
  "clippingMaskMode": 0,
  "do_objectID": "3A248AB8-15E4-428B-8E82-FCBF10923F30",
  "edited": true,
  "exportOptions": {
    "_class": "exportOptions",
    "exportFormats": [
    ],
    "includedLayerIds": [
    ],
    "layerOptions": 0,
    "shouldTrim": false
  },
  "frame": {
    "_class": "rect",
    "constrainProportions": false,
    "height": 13,
    "width": 13,
    "x": 59,
    "y": 25
  },
  "hasClippingMask": false,
  "isClosed": false,
  "isFixedToViewport": false,
  "isFlippedHorizontal": false,
  "isFlippedVertical": false,
  "isLocked": false,
  "isVisible": true,
  "layerListExpandedType": 0,
  "name": "Fill 11",
  "nameIsFixed": false,
  "pointRadiusBehaviour": 1,
  "points": [
    {
      "_class": "curvePoint",
      "cornerRadius": 0,
      "curveFrom": "{1, 0.77619744823258729}",
      "curveMode": 4,
      "curveTo": "{1, 0.50010458063166696}",
      "hasCurveFrom": true,
      "hasCurveTo": false,
      "point": "{1, 0.50010458063166696}"
    },
    {
      "_class": "curvePoint",
      "cornerRadius": 0,
      "curveFrom": "{0.22389542483660113, 1}",
      "curveMode": 2,
      "curveTo": "{0.77618300653594752, 1}",
      "hasCurveFrom": true,
      "hasCurveTo": true,
      "point": "{0.50007843137254937, 1}"
    },
    {
      "_class": "curvePoint",
      "cornerRadius": 0,
      "curveFrom": "{0, 0.22390713239907947}",
      "curveMode": 2,
      "curveTo": "{0, 0.77619744823258729}",
      "hasCurveFrom": true,
      "hasCurveTo": true,
      "point": "{0, 0.50010458063166696}"
    },
    {
      "_class": "curvePoint",
      "cornerRadius": 0,
      "curveFrom": "{0.77618300653594752, 0}",
      "curveMode": 2,
      "curveTo": "{0.22389542483660113, 0}",
      "hasCurveFrom": true,
      "hasCurveTo": true,
      "point": "{0.50007843137254937, 0}"
    },
    {
      "_class": "curvePoint",
      "cornerRadius": 0,
      "curveFrom": "{1, 0.50010458063166696}",
      "curveMode": 4,
      "curveTo": "{1, 0.22390713239907947}",
      "hasCurveFrom": false,
      "hasCurveTo": true,
      "point": "{1, 0.50010458063166696}"
    }
  ],
  "resizingConstraint": 63,
  "resizingType": 0,
  "rotation": 0,
  "shouldBreakMaskChain": false,
  "style": {
    "_class": "style",
    "endMarkerType": 0,
    "fills": [
      {
        "_class": "fill",
        "color": {
          "_class": "color",
          "alpha": 1,
          "blue": 0.07100000000000001,
          "green": 0.898,
          "red": 1
        },
        "fillType": 0,
        "isEnabled": true,
        "noiseIndex": 0,
        "noiseIntensity": 0,
        "patternFillType": 1,
        "patternTileScale": 1
      }
    ],
    "miterLimit": 10,
    "startMarkerType": 0,
    "windingRule": 1
  }
}