{
  "_class": "shapePath",
  "booleanOperation": -1,
  "clippingMaskMode": 0,
  "do_objectID": "EFBE4704-BB94-4DCD-B13F-33B51BB74535",
  "edited": true,
  "exportOptions": {
    "_class": "exportOptions",
    "exportFormats": [
    ],
    "includedLayerIds": [
    ],
    "layerOptions": 0,
    "shouldTrim": false
  },
  "frame": {
    "_class": "rect",
    "constrainProportions": false,
    "height": 14.609,
    "width": 11.374,
    "x": 178.8086,
    "y": 13.8711
  },
  "hasClippingMask": false,
  "isClosed": true,
  "isFixedToViewport": false,
  "isFlippedHorizontal": false,
  "isFlippedVertical": false,
  "isLocked": false,
  "isVisible": true,
  "layerListExpandedType": 0,
  "name": "Fill 28",
  "nameIsFixed": false,
  "pointRadiusBehaviour": 1,
  "points": [
    {
      "_class": "curvePoint",
      "cornerRadius": 0,
      "curveFrom": "{0, 0}",
      "curveMode": 1,
      "curveTo": "{0, 0}",
      "hasCurveFrom": false,
      "hasCurveTo": false,
      "point": "{0, 0}"
    },
    {
      "_class": "curvePoint",
      "cornerRadius": 0,
      "curveFrom": "{0.26261649375769264, 0}",
      "curveMode": 1,
      "curveTo": "{0.26261649375769264, 0}",
      "hasCurveFrom": false,
      "hasCurveTo": false,
      "point": "{0.26261649375769264, 0}"
    },
    {
      "_class": "curvePoint",
      "cornerRadius": 0,
      "curveFrom": "{0.50219799542816879, 0.35977821890615369}",
      "curveMode": 1,
      "curveTo": "{0.50219799542816879, 0.35977821890615369}",
      "hasCurveFrom": false,
      "hasCurveTo": false,
      "point": "{0.50219799542816879, 0.35977821890615369}"
    },
    {
      "_class": "curvePoint",
      "cornerRadius": 0,
      "curveFrom": "{0.74072445929312603, 0}",
      "curveMode": 1,
      "curveTo": "{0.74072445929312603, 0}",
      "hasCurveFrom": false,
      "hasCurveTo": false,
      "point": "{0.74072445929312603, 0}"
    },
    {
      "_class": "curvePoint",
      "cornerRadius": 0,
      "curveFrom": "{1, 0}",
      "curveMode": 1,
      "curveTo": "{1, 0}",
      "hasCurveFrom": false,
      "hasCurveTo": false,
      "point": "{1, 0}"
    },
    {
      "_class": "curvePoint",
      "cornerRadius": 0,
      "curveFrom": "{0.62405486196588855, 0.56697925936066806}",
      "curveMode": 1,
      "curveTo": "{0.62405486196588855, 0.56697925936066806}",
      "hasCurveFrom": false,
      "hasCurveTo": false,
      "point": "{0.62405486196588855, 0.56697925936066806}"
    },
    {
      "_class": "curvePoint",
      "cornerRadius": 0,
      "curveFrom": "{0.62405486196588855, 1}",
      "curveMode": 1,
      "curveTo": "{0.62405486196588855, 1}",
      "hasCurveFrom": false,
      "hasCurveTo": false,
      "point": "{0.62405486196588855, 1}"
    },
    {
      "_class": "curvePoint",
      "cornerRadius": 0,
      "curveFrom": "{0.377703534376648, 1}",
      "curveMode": 1,
      "curveTo": "{0.377703534376648, 1}",
      "hasCurveFrom": false,
      "hasCurveTo": false,
      "point": "{0.377703534376648, 1}"
    },
    {
      "_class": "curvePoint",
      "cornerRadius": 0,
      "curveFrom": "{0.377703534376648, 0.56697925936066806}",
      "curveMode": 1,
      "curveTo": "{0.377703534376648, 0.56697925936066806}",
      "hasCurveFrom": false,
      "hasCurveTo": false,
      "point": "{0.377703534376648, 0.56697925936066806}"
    }
  ],
  "resizingConstraint": 63,
  "resizingType": 0,
  "rotation": 0,
  "shouldBreakMaskChain": false,
  "style": {
    "_class": "style",
    "endMarkerType": 0,
    "fills": [
      {
        "_class": "fill",
        "color": {
          "_class": "color",
          "alpha": 1,
          "blue": 0.7402985692024231,
          "green": 0.6066672205924988,
          "red": 0.3372964262962341
        },
        "fillType": 0,
        "isEnabled": true,
        "noiseIndex": 0,
        "noiseIntensity": 0,
        "patternFillType": 1,
        "patternTileScale": 1
      }
    ],
    "miterLimit": 10,
    "startMarkerType": 0,
    "windingRule": 1
  }
}